Workbook

Sheet Start Here
A1: Modern Stock Valuation Cheat Sheet & Workbook
A3: How to use this workbook
A4: Step | B4: Action | C4: Sheet | D4: Tip
A5: 1 | B5: Enter company data and assumptions | C5: Assumptions | D5: Yellow cells with blue text are hardcoded inputs you should update.
A6: 2 | B6: Review valuation outputs | C6: Dashboard | D6: Compare several methods instead of relying on one single model.
A7: 3 | B7: Stress test growth and discount assumptions | C7: DCF Calculator | D7: Small changes in discount rate or terminal growth can move value a lot.
A8: 4 | B8: Check quality and risk | C8: Quality & Growth / Balance Safety | D8: High ROIC and solid interest coverage usually deserve more confidence.
A9: 5 | B9: Document source data | C9: Sources & Notes | D9: Replace all placeholder examples with filings, data provider outputs, or your own research notes.
A11: Color conventions
A12: Color / style | B12: Meaning | C12: Where used | D12: Reminder
A13: Blue text + yellow fill | B13: Hardcoded input | C13: Assumptions and editable assumptions in calculators | D13: Change these when analyzing a real company.
A14: Black text | B14: Formula / calculation | C14: Most output cells | D14: Do not overwrite unless you intentionally rebuild the model.
A15: Green text | B15: Cross-sheet link | C15: Dashboard and linked inputs | D15: These pull from another worksheet.
A16: Dark blue section header | B16: Model section | C16: All sheets | D16: Helps separate unrelated calculations.
A18: Best calculation by company type
A19: Company type | B19: Primary methods | C19: Quality checks | D19: Watch-outs | E19: Best quick metric
A20: Mature profitable | B20: FCF yield, DCF, EV/EBIT, P/E | C20: ROIC vs WACC, FCF per share | D20: Flat growth, buybacks masking weak operations | E20: FCF yield
A21: Growth / SaaS | B21: Long-term DCF, Rule of 40, EV/Revenue with margin context | C21: Revenue retention, FCF margin, dilution | D21: Stock-based comp and unrealistic terminal margins | E21: Rule of 40
A22: Banks / insurers | B22: Residual income, ROE, P/B, justified P/B | C22: Credit quality, capital ratios, reserve adequacy | D22: Book value quality and credit-cycle losses | E22: ROE vs cost of equity
A23: Cyclical / commodity | B23: Normalized EV/EBITDA, trough leverage, replacement value | C23: Balance sheet survival at cycle lows | D23: Peak earnings looking deceptively cheap | E23: Normalized EV/EBITDA
A24: Asset-heavy | B24: ROIC, maintenance CapEx, EV/EBIT, debt coverage | C24: CapEx intensity, asset turnover | D24: Accounting earnings overstating cash flow | E24: ROIC spread
A25: Conglomerate | B25: Sum-of-the-parts and segment multiples | C25: Segment-level margins and capital intensity | D25: Corporate overhead and hidden liabilities | E25: SOTP discount/premium
A27: Important: this workbook is educational and uses placeholder assumptions. Replace the examples with current company-specific data before making any investment decision.

Sheet Assumptions
A1: Input Assumptions and Example Data
A3: Metric | B3: Value | C3: Units | D3: Type | E3: Formula / Tip | F3: Source / Notes
A4: Company Name | B4: NVIDIA Corporation | C4: Text | D4: Input | E4: Replace with target company. | F4: FMP profile, pulled 2026-06-01.
A5: Ticker | B5: NVDA | C5: Text | D5: Input | E5: Replace with ticker. | F5: FMP quote/profile symbol.
A6: Scenario | B6: Base | C6: Dropdown | D6: Input | E6: Use Conservative, Base, or Optimistic. | F6: Scenario left as Base; manual scenario assumption.
A7: Current Share Price | B7: 224.36 | C7: $/sh | D7: Input | E7: Latest market price. | F7: FMP quote price, pulled 2026-06-01.
A8: Diluted Shares | B8: 24221 | C8: mm | D8: Input | E8: Use diluted weighted-average shares or fully diluted share count. | F8: FMP shares-float outstandingShares / 1e6. Diluted FY weighted average was 24,514mm.
A9: Market Cap | B9: =B7*B8 | C9: $mm | D9: Formula | E9: Current Share Price × Diluted Shares. | F9: Formula retained from workbook.
A10: Cash & Investments | B10: 62556 | C10: $mm | D10: Input | E10: Cash, equivalents, and marketable securities. | F10: FMP FY2026 balance sheet: cashAndShortTermInvestments / 1e6.
A11: Total Debt | B11: 11412 | C11: $mm | D11: Input | E11: Short-term + long-term debt. | F11: FMP FY2026 balance sheet: totalDebt / 1e6.
A12: Preferred + Minority Interest | B12: 0 | C12: $mm | D12: Input | E12: Include if material. | F12: FMP FY2026 balance sheet: preferredStock and minorityInterest reported as 0.
A13: Net Debt | B13: =B11+B12-B10 | C13: $mm | D13: Formula | E13: Debt + pref./minority interest − cash. | F13: Formula retained from workbook.
A14: Enterprise Value | B14: =B9+B13 | C14: $mm | D14: Formula | E14: Market cap + net debt. | F14: Formula retained from workbook.
A15: EPS Current | B15: 6.5722227 | C15: $/sh | D15: Input | E15: Use normalized or forward EPS consistently. | F15: FMP ratios TTM: netIncomePerShareTTM.
A16: Book Value per Share | B16: 8.0488347 | C16: $/sh | D16: Input | E16: Useful for banks/insurers and residual income. | F16: FMP ratios TTM: bookValuePerShareTTM.
A17: FCF per Share Current | B17: 4.9030717 | C17: $/sh | D17: Input | E17: Operating cash flow minus CapEx, divided by diluted shares. | F17: FMP ratios TTM: freeCashFlowPerShareTTM.
A18: Revenue | B18: 215938 | C18: $mm | D18: Input | E18: Total revenue. | F18: FMP FY2026 income statement: revenue / 1e6.
A19: EBIT | B19: 141709 | C19: $mm | D19: Input | E19: Operating income before interest and taxes. | F19: FMP FY2026 income statement: EBIT / 1e6.
A20: EBITDA | B20: 144552 | C20: $mm | D20: Input | E20: EBIT + D&A; use adjusted carefully. | F20: FMP FY2026 income statement: EBITDA / 1e6.
A21: Interest Expense | B21: 259 | C21: $mm | D21: Input | E21: Annual interest expense. | F21: FMP FY2026 income statement: interestExpense / 1e6.
A22: Current Assets | B22: 125605 | C22: $mm | D22: Input | E22: Used for current ratio. | F22: FMP FY2026 balance sheet: totalCurrentAssets / 1e6.
A23: Current Liabilities | B23: 32163 | C23: $mm | D23: Input | E23: Used for current ratio. | F23: FMP FY2026 balance sheet: totalCurrentLiabilities / 1e6.
A24: Invested Capital | B24: 143528 | C24: $mm | D24: Input | E24: Debt + equity − non-operating cash, or operating assets minus operating liabilities. | F24: FMP key metrics TTM: investedCapitalTTM / 1e6.
A25: Tax Rate | B25: 0.15746161 | C25: % | D25: Input | E25: Normalized cash tax rate. | F25: FMP ratios TTM: effectiveTaxRateTTM.
A26: EPS Growth Rate | B26: 0.66666667 | C26: % | D26: Input | E26: Expected annual EPS growth. | F26: Derived from FMP FY2026 vs FY2025 diluted EPS: 4.90 / 2.94 - 1. Review before use.
... A41: Margin of Safety | B41: 0.25 | C41: % | D41: Input | E41: Discount to fair value before considering a buy zone. | F41: Manual margin-of-safety assumption left at 25%.
A42: Base-year Total FCF | B42: =B17*B8 | C42: $mm | D42: Formula | E42: FCF/share × diluted shares. | F42: Formula retained from workbook.
A43: Notes | B43: Filled from FMP quote/profile, FY2026 annual statements, TTM ratios/key metrics, and shares float on 2026-06-01. Growth/multiple/discount-rate fields are source-backed baselines or manual assumptions and should be reviewed before investment use. | C43: Text | D43: Input | E43: Document assumptions here. | F43: Generated by My_Data workbook fill on 2026-06-01.
A45: FMP Fill Audit
A46: Quote price | B46: 224.36 | C46: FMP quote, pulled 2026-06-01
A47: Quote market cap | B47: 5,434,223.56 $mm | C47: FMP quote marketCap / 1e6
A48: Shares used | B48: 24,221.0 mm | C48: FMP shares-float outstandingShares / 1e6
A49: Latest annual fiscal year | B49: FY2026, period ended 2026-01-25 | C49: FMP income, balance sheet, cash flow statements
A50: TTM metrics date | B50: Pulled 2026-06-01 | C50: FMP key-metrics-ttm and ratios-ttm
A51: Manual fields retained | B51: Terminal growth, WACC, cost of equity, AAA yield, margin of safety | C51: Review before investment use

Sheet Dashboard
A1: Valuation Dashboard
A3: Company | B3: =Assumptions!B4 | C3: Ticker | D3: =Assumptions!B5 | E3: Scenario | F3: =Assumptions!B6 | G3: Current Price | H3: =Assumptions!B7
A5: Value outputs
A6: Method | B6: Value / Share | C6: Current Price | D6: Upside / (Downside) | E6: Buy Zone | F6: Status | G6: Best use / caveat
A7: Graham adjusted growth formula | B7: ='Graham & Multiples'!B13 | C7: =Assumptions!B7 | D7: =B7/C7-1 | E7: =B7*(1-Assumptions!B41) | F7: =IF(C7<=E7,"Below buy zone",IF(C7<=B7,"Below fair value","Above fair value")) | G7: Rough historical screen; very sensitive to growth and bond yield.
A8: Single-stage FCF perpetuity | B8: ='DCF Calculator'!B10 | C8: =Assumptions!B7 | D8: =B8/C8-1 | E8: =B8*(1-Assumptions!B41) | F8: =IF(C8<=E8,"Below buy zone",IF(C8<=B8,"Below fair value","Above fair value")) | G8: Best for stable FCF businesses; not for volatile or fast-changing firms.
A9: 5-year FCF/share DCF | B9: ='DCF Calculator'!B25 | C9: =Assumptions!B7 | D9: =B9/C9-1 | E9: =B9*(1-Assumptions!B41) | F9: =IF(C9<=E9,"Below buy zone",IF(C9<=B9,"Below fair value","Above fair value")) | G9: More flexible; still depends heavily on terminal assumptions.
A10: Residual income | B10: ='Residual & Justified'!B28 | C10: =Assumptions!B7 | D10: =B10/C10-1 | E10: =B10*(1-Assumptions!B41) | F10: =IF(C10<=E10,"Below buy zone",IF(C10<=B10,"Below fair value","Above fair value")) | G10: Useful when book value matters, especially banks/insurers.
A11: Justified P/E | B11: ='Residual & Justified'!B29 | C11: =Assumptions!B7 | D11: =B11/C11-1 | E11: =B11*(1-Assumptions!B41) | F11: =IF(C11<=E11,"Below buy zone",IF(C11<=B11,"Below fair value","Above fair value")) | G11: Simple stable-growth sanity check.
A12: Justified P/B | B12: ='Residual & Justified'!B30 | C12: =Assumptions!B7 | D12: =B12/C12-1 | E12: =B12*(1-Assumptions!B41) | F12: =IF(C12<=E12,"Below buy zone",IF(C12<=B12,"Below fair value","Above fair value")) | G12: Good for book-value-heavy financials.
A13: Target P/E | B13: ='Graham & Multiples'!B27 | C13: =Assumptions!B7 | D13: =B13/C13-1 | E13: =B13*(1-Assumptions!B41) | F13: =IF(C13<=E13,"Below buy zone",IF(C13<=B13,"Below fair value","Above fair value")) | G13: Relative valuation; only as good as peer multiple choice.
A14: Target EV/EBIT | B14: ='Graham & Multiples'!B28 | C14: =Assumptions!B7 | D14: =B14/C14-1 | E14: =B14*(1-Assumptions!B41) | F14: =IF(C14<=E14,"Below buy zone",IF(C14<=B14,"Below fair value","Above fair value")) | G14: Capital-structure-aware operating multiple.
A15: Target EV/EBITDA | B15: ='Graham & Multiples'!B29 | C15: =Assumptions!B7 | D15: =B15/C15-1 | E15: =B15*(1-Assumptions!B41) | F15: =IF(C15<=E15,"Below buy zone",IF(C15<=B15,"Below fair value","Above fair value")) | G15: Useful for capital-intensive or acquisition comparisons; watch CapEx.
A18: Summary statistics
A19: Average Fair Value / Share | B19: =AVERAGE(B7:B15) | D19: Interpretation guide
A20: Median Fair Value / Share | B20: =MEDIAN(B7:B15) | D20: Below buy zone | E20: Price is below fair value after margin of safety.
A21: High Fair Value / Share | B21: =MAX(B7:B15) | D21: Below fair value | E21: Price is below model value, but not necessarily cheap enough.
A22: Low Fair Value / Share | B22: =MIN(B7:B15) | D22: Above fair value | E22: Price is above this method's estimate.
A23: Average Buy Zone | B23: =AVERAGE(E7:E15) | D23: Reality check | E23: Confirm fundamentals before acting.

Sheet Graham & Multiples
A1: Graham Formula, 2g, and Quick Multiples
A3: Graham growth formula | D3: Worked example: growth rate → 2g
A4: Item | B4: Value | C4: Tip | D4: Growth Rate | E4: 2g Term | F4: Example EPS | G4: 8.5 + 2g | H4: Adjusted Value
A5: EPS | B5: =Assumptions!B15 | C5: Use normalized EPS, not a one-time boom year. | D5: 0 | E5: =2*D5*100 | F5: =Assumptions!B15 | G5: =8.5+E5 | H5: =F5*G5*4.4/(Assumptions!B37*100)
A6: Expected EPS Growth Rate | B6: =Assumptions!B26 | C6: Enter as normal percent rate in Assumptions, e.g., 8%. | D6: 0.05 | E6: =2*D6*100 | F6: =Assumptions!B15 | G6: =8.5+E6 | H6: =F6*G6*4.4/(Assumptions!B37*100)
A7: 2g Term | B7: =2*B6*100 | C7: Formula converts 8% growth into 16 for Graham's 2g term. | D7: 0.08 | E7: =2*D7*100 | F7: =Assumptions!B15 | G7: =8.5+E7 | H7: =F7*G7*4.4/(Assumptions!B37*100)
A8: No-growth P/E baseline | B8: 8.5 | C8: Graham's baseline P/E for no-growth company. | D8: 0.1 | E8: =2*D8*100 | F8: =Assumptions!B15 | G8: =8.5+E8 | H8: =F8*G8*4.4/(Assumptions!B37*100)
A9: 8.5 + 2g | B9: =B8+B7 | C9: Growth-adjusted valuation bracket. | D9: 0.12 | E9: =2*D9*100 | F9: =Assumptions!B15 | G9: =8.5+E9 | H9: =F9*G9*4.4/(Assumptions!B37*100)
A10: Original Graham Value | B10: =B5*B9 | C10: EPS × (8.5 + 2g). | D10: 0.15 | E10: =2*D10*100 | F10: =Assumptions!B15 | G10: =8.5+E10 | H10: =F10*G10*4.4/(Assumptions!B37*100)
A11: Reference bond yield | B11: 4.4 | C11: Graham's historical bond-yield adjustment reference.
A12: Current AAA Yield | B12: =Assumptions!B37 | C12: Use current AAA corporate bond yield; example pulled from Assumptions.
A13: Adjusted Graham Value | B13: =B10*B11/(B12*100) | C13: Original value × 4.4 ÷ current AAA yield percentage number.
A14: Buy Zone after MOS | B14: =B13*(1-Assumptions!B41) | C14: Adjusted value × (1 − margin of safety).
A15: Current Price | B15: =Assumptions!B7 | C15: Linked from Assumptions.
A16: Upside / (Downside) | B16: =B13/B15-1 | C16: Adjusted Graham value ÷ current price − 1.
A18: Modern quick multiples
A19: Metric | B19: Result | C19: Formula | D19: When useful | E19: Tip
A20: Current P/E | B20: =Assumptions!B7/Assumptions!B15 | C20: Price ÷ EPS | D20: Quick earnings comparison | E20: Compare only within similar industries and growth profiles.
A21: PEG Ratio | B21: =B20/(Assumptions!B26*100) | C21: P/E ÷ EPS growth % | D21: Growth vs valuation screen | E21: Use expected growth as a percentage number; lower is not always better.
A22: FCF Yield | B22: =Assumptions!B17/Assumptions!B7 | C22: FCF/share ÷ price | D22: Modern cash-flow sanity check | E22: Compare to Treasury/corporate bond yields and required return.
A23: EV/EBIT | B23: =Assumptions!B14/Assumptions!B19 | C23: Enterprise value ÷ EBIT | D23: Capital-structure-aware operating multiple | E23: Often cleaner than P/E when tax/debt structures differ.
A24: EV/EBITDA | B24: =Assumptions!B14/Assumptions!B20 | C24: Enterprise value ÷ EBITDA | D24: Acquisition and capital-intensive comparisons | E24: Can hide CapEx intensity.
A25: EV/Revenue | B25: =Assumptions!B14/Assumptions!B18 | C25: Enterprise value ÷ revenue | D25: Early-stage/growth companies | E25: Only meaningful with margin and growth context.
A26: Earnings Yield | B26: =Assumptions!B15/Assumptions!B7 | C26: EPS ÷ price | D26: Inverse of P/E | E26: Compare to required return; quality matters.
A27: Target P/E Value / Share | B27: =Assumptions!B15*Assumptions!B38 | C27: EPS × target P/E | D27: Relative valuation cross-check | E27: Use a conservative peer multiple.
A28: Target EV/EBIT Value / Share | B28: =(Assumptions!B19*Assumptions!B39-Assumptions!B13)/Assumptions!B8 | C28: (EBIT × target EV/EBIT − net debt) ÷ shares | D28: Operating multiple valuation | E28: Subtract net debt before dividing by shares.
A29: Target EV/EBITDA Value / Share | B29: =(Assumptions!B20*Assumptions!B40-Assumptions!B13)/Assumptions!B8 | C29: (EBITDA × target EV/EBITDA − net debt) ÷ shares | D29: Operating multiple valuation | E29: Use with caution if maintenance CapEx is high.

Sheet DCF Calculator
A1: Free Cash Flow DCF Calculator
A3: Single-stage FCF perpetuity
A4: Item | B4: Value | C4: Tip
A5: Current FCF / Share | B5: =Assumptions!B17 | C5: Use durable free cash flow, not a one-time spike.
A6: FCF Growth Rate | B6: =Assumptions!B27 | C6: Next-year growth assumption.
A7: Next-year FCF / Share | B7: =B5*(1+B6) | C7: Current FCF/share × (1 + growth).
A8: Discount Rate / WACC | B8: =Assumptions!B30 | C8: Required return.
A9: Terminal Growth Rate | B9: =Assumptions!B29 | C9: Must be less than discount rate.
A10: Single-stage Value / Share | B10: =IF(B8>B9,B7/(B8-B9),NA()) | C10: Next-year FCF/share ÷ (discount rate − terminal growth).
A11: Buy Zone after MOS | B11: =B10*(1-Assumptions!B41) | C11: Value × (1 − margin of safety).
A12: Current Price | B12: =Assumptions!B7 | C12: Linked from Assumptions.
A13: Upside / (Downside) | B13: =B10/B12-1 | C13: Value ÷ current price − 1.
A16: 5-year FCF/share DCF
B17: Year 0 | C17: Year 1 | D17: Year 2 | E17: Year 3 | F17: Year 4 | G17: Year 5
A18: Growth Rate | B18: - | C18: 0.07 | D18: 0.06 | E18: 0.05 | F18: 0.04 | G18: 0.035 | H18: Tip
A19: FCF / Share | B19: =Assumptions!B17 | C19: =B19*(1+C18) | D19: =C19*(1+D18) | E19: =D19*(1+E18) | F19: =E19*(1+F18) | G19: =F19*(1+G18) | H19: Year-by-year DCF is usually more useful than a one-line perpetuity because it lets you fade high growth toward a realistic terminal rate. For firm-level DCF, forecast FCFF in $mm, subtract net debt, then divide by diluted shares.
A20: Discount Factor | C20: =1/(1+Assumptions!B30)^1 | D20: =1/(1+Assumptions!B30)^2 | E20: =1/(1+Assumptions!B30)^3 | F20: =1/(1+Assumptions!B30)^4 | G20: =1/(1+Assumptions!B30)^5
A21: PV of FCF | C21: =C19*C20 | D21: =D19*D20 | E21: =E19*E20 | F21: =F19*F20 | G21: =G19*G20
A22: Terminal Value | G22: =IF(Assumptions!B30>Assumptions!B29,G19*(1+Assumptions!B29)/(Assumptions!B30-Assumptions!B29),NA())
A23: PV of Terminal Value | G23: =G22*G20
A25: 5-year DCF Value / Share | B25: =SUM(C21:G21)+G23
A26: Buy Zone after MOS | B26: =B25*(1-Assumptions!B41)
A27: Current Price | B27: =Assumptions!B7
A28: Upside / (Downside) | B28: =B25/B27-1

Sheet Quality & Growth
A1: Quality, Reinvestment, and Per-Share Growth
A3: ROIC and economic profit | E3: Dilution-adjusted per-share growth example
A4: Item | B4: Value | C4: Tip | E4: Metric | F4: Year 1 | G4: Year 2 | H4: Growth
A5: EBIT | B5: =Assumptions!B19 | C5: Operating income before interest and taxes. | E5: Total FCF ($mm) | F5: 1000 | G5: 1200 | H5: =G5/F5-1
A6: Tax Rate | B6: =Assumptions!B25 | C6: Use normalized cash tax rate. | E6: Diluted Shares (mm) | F6: 100 | G6: 120 | H6: =G6/F6-1
A7: NOPAT | B7: =B5*(1-B6) | C7: EBIT × (1 − tax rate). | E7: FCF / Share | F7: =F5/F6 | G7: =G5/G6 | H7: =G7/F7-1
A8: Invested Capital | B8: =Assumptions!B24 | C8: Capital actually required to operate business. | E8: Company-level FCF growth | H8: =H5
A9: Calculated ROIC | B9: =B7/B8 | C9: NOPAT ÷ invested capital. | E9: Per-share FCF growth | H9: =H7
A10: WACC | B10: =Assumptions!B30 | C10: Required return / cost of capital.
A11: ROIC Spread | B11: =B9-B10 | C11: ROIC − WACC. Positive spread creates value. | E11: Why this matters: a company can grow total free cash flow but fail to grow FCF per share if share count rises too quickly. Always check diluted share count and stock-based compensation.
A12: Economic Profit | B12: =B7-(B10*B8) | C12: NOPAT − (WACC × invested capital).
A13: Interpretation | B13: =IF(B11>0.05,"Strong value creation",IF(B11>0,"Positive spread","Watch: ROIC below WACC")) | C13: Value creators earn ROIC above WACC.
A16: Growth from reinvestment
A17: Item | B17: Value | C17: Tip
A18: Reinvestment Rate | B18: =Assumptions!B33 | C18: Reinvestment ÷ NOPAT.
A19: ROIC Assumption | B19: =Assumptions!B34 | C19: Forward ROIC assumption.
A20: Fundamental Growth Estimate | B20: =B18*B19 | C20: Reinvestment rate × ROIC.
A21: Compare to EPS Growth Assumption | B21: =Assumptions!B26 | C21: If assumed growth is much higher, investigate why.
A24: Rule of 40
A25: Item | B25: Value | C25: Tip
A26: Revenue Growth Rate | B26: =Assumptions!B28 | C26: Growth component.
A27: FCF Margin | B27: =Assumptions!B35 | C27: Profitability component.
A28: Rule of 40 Score | B28: =B26+B27 | C28: Revenue growth + FCF margin.
A29: Interpretation | B29: =IF(B28>=0.4,"Strong balance of growth + margin",IF(B28>=0.25,"Okay / needs context","Weak or early-stage")) | C29: >= 40% is commonly considered strong for SaaS/software.

Sheet Residual & Justified
A1: Residual Income and Justified Multiples
A3: Residual income value
A4: Item | B4: Value | C4: Tip
A5: Book Value / Share | B5: =Assumptions!B16 | C5: Starting equity value on the balance sheet.
A6: EPS | B6: =Assumptions!B15 | C6: Use normalized EPS.
A7: Cost of Equity | B7: =Assumptions!B31 | C7: Required return for equity investors.
A8: Residual Income Growth | B8: =Assumptions!B29 | C8: Use conservative long-run growth.
A9: Equity Charge / Share | B9: =B5*B7 | C9: Book value × cost of equity.
A10: Residual Income / Share | B10: =B6-B9 | C10: EPS − equity charge.
A11: Residual Income Value Add | B11: =IF(B7>B8,B10/(B7-B8),NA()) | C11: Residual income ÷ (cost of equity − growth).
A12: Residual Income Fair Value / Share | B12: =B5+B11 | C12: Book value + PV residual income.
A13: Buy Zone after MOS | B13: =B12*(1-Assumptions!B41) | C13: Value × (1 − margin of safety).
A14: Current Price | B14: =Assumptions!B7 | C14: Linked from Assumptions.
A15: Upside / (Downside) | B15: =B12/B14-1 | C15: Value ÷ current price − 1.
A18: Justified P/E | E18: Justified P/B
A19: Item | B19: Value | C19: Tip | E19: Item | F19: Value | G19: Formula | H19: Tip
A20: Payout Ratio | B20: =Assumptions!B32 | C20: Stable payout ratio. | E20: ROE | F20: =Assumptions!B15/Assumptions!B16 | G20: EPS ÷ book value/share | H20: Higher sustainable ROE deserves higher P/B.
A21: Cost of Equity | B21: =Assumptions!B31 | C21: Required equity return. | E21: Stable Growth Rate | F21: =Assumptions!B29 | G21: Linked from terminal growth | H21: Keep conservative.
A22: Stable Growth Rate | B22: =Assumptions!B29 | C22: Use conservative long-run rate. | E22: Cost of Equity | F22: =Assumptions!B31 | G22: Linked from assumptions | H22: Required equity return.
A23: Justified P/E | B23: =IF(B21>B22,B20/(B21-B22),NA()) | C23: Payout ratio ÷ (cost of equity − growth). | E23: Justified P/B | F23: =IF(F22>F21,(F20-F21)/(F22-F21),NA()) | G23: (ROE − growth) ÷ (cost of equity − growth) | H23: Useful for banks/insurers.
A24: Fair Value / Share | B24: =B23*Assumptions!B15 | C24: EPS × justified P/E. | E24: Fair Value / Share | F24: =F23*Assumptions!B16 | G24: Book value/share × justified P/B | H24: Compare to current price.
A27: Dashboard output helpers
A28: Residual Income Value / Share | B28: =B12 | C28: Linked from B12.
A29: Justified P/E Value / Share | B29: =B24 | C29: Linked from B24.
A30: Justified P/B Value / Share | B30: =F24 | C30: Linked from F24.

Sheet Balance Safety
A1: Balance Sheet and Downside Safety Checks
A3: Core credit and liquidity ratios
A4: Item | B4: Value | C4: Status | D4: Tip
A5: Net Debt | B5: =Assumptions!B13 | D5: Debt + preferred/minority interest − cash.
A6: EBITDA | B6: =Assumptions!B20 | D6: Used for debt capacity checks.
A7: Net Debt / EBITDA | B7: =B5/B6 | C7: =IF(B7<2,"Strong",IF(B7<=4,"Watch","Risky")) | D7: <2x usually safer; 2–4x watch; >4x risky unless very stable.
A8: EBIT | B8: =Assumptions!B19 | D8: Used for interest coverage.
A9: Interest Expense | B9: =Assumptions!B21 | D9: Annual interest cost.
A10: Interest Coverage | B10: =B8/B9 | C10: =IF(B10>6,"Strong",IF(B10>=3,"Watch","Risky")) | D10: >6x strong; 3–6x watch; <3x risky.
A11: Current Assets | B11: =Assumptions!B22 | D11: Liquid/near-term assets.
A12: Current Liabilities | B12: =Assumptions!B23 | D12: Near-term liabilities.
A13: Current Ratio | B13: =B11/B12 | C13: =IF(B13>1.5,"Strong",IF(B13>=1,"Watch","Risky")) | D13: >1.5x strong; 1.0–1.5x watch; <1.0x potential liquidity issue.
A16: Safety ratio interpretation guide
A17: Ratio | B17: Stronger | C17: Watch | D17: Risky | E17: Important context
A18: Net Debt / EBITDA | B18: < 2.0x | C18: 2.0x – 4.0x | D18: > 4.0x | E18: Stable utilities can support more leverage; cyclicals usually need less.
A19: Interest Coverage | B19: > 6.0x | C19: 3.0x – 6.0x | D19: < 3.0x | E19: Rising rates or refinancing walls can worsen coverage quickly.
A20: Current Ratio | B20: > 1.5x | C20: 1.0x – 1.5x | D20: < 1.0x | E20: Inventory-heavy firms can look safer than they are if inventory is slow-moving.
A21: FCF Conversion | B21: > 80% of net income | C21: 50% – 80% | D21: < 50% | E21: Weak conversion can mean earnings are not turning into cash.
A22: Debt Maturity Wall | B22: Staggered | C22: Some concentration | D22: Large near-term maturity | E22: High refinancing needs can create equity risk.

Sheet Checklist
A1: Modern Valuation Checklist
A3: Checklist for evaluating a stock
A4: Area | B4: Question | C4: Good sign | D4: Red flag | E4: Calculation | F4: Tip
A5: Value | B5: Is the stock cheap relative to durable cash flow? | C5: FCF yield comfortably above required return after growth context. | D5: Low FCF yield with weak or slowing growth. | E5: FCF Yield = FCF ÷ Market Cap | F5: Use FCF, not just EPS.
A6: Value | B6: Do multiple methods point to similar value? | C6: DCF, multiples, and residual income are directionally consistent. | D6: Only one aggressive method shows upside. | E6: Dashboard comparison | F6: Use a valuation range, not a single number.
A7: Growth | B7: Is growth economically supported? | C7: Reinvestment × ROIC supports assumed growth. | D7: Growth depends only on multiple expansion. | E7: Growth ≈ Reinvestment Rate × ROIC | F7: Avoid paying for growth that destroys value.
A8: Quality | B8: Does the company create value? | C8: ROIC is meaningfully above WACC. | D8: ROIC below WACC but management keeps expanding. | E8: ROIC − WACC | F8: High ROIC businesses deserve more attention.
A9: Cash flow | B9: Are earnings converting to cash? | C9: FCF grows with earnings over time. | D9: Accounting earnings rise while cash flow lags. | E9: FCF / Net Income | F9: Watch working-capital swings.
A10: Dilution | B10: Are shareholders actually getting per-share growth? | C10: FCF per share grows over time. | D10: Total FCF rises but share count rises just as fast. | E10: FCF/share growth | F10: Always check diluted shares.
A11: Balance sheet | B11: Can the company survive a downturn? | C11: Low net leverage and high interest coverage. | D11: High leverage and near-term maturities. | E11: Net Debt/EBITDA; Interest Coverage | F11: Cheap stocks with weak balance sheets can stay cheap.
A12: Margins | B12: Are margins durable? | C12: Stable/improving margins with pricing power. | D12: Margins boosted by temporary cost cuts. | E12: Gross/EBIT/FCF margin trend | F12: Compare to peers and prior cycles.
A13: Moat | B13: Why does the company earn returns above peers? | C13: Switching costs, network effects, scale, brand, cost advantage. | D13: No clear advantage but premium valuation. | E13: ROIC stability | F13: Qualitative moat explains quantitative returns.
A14: Management | B14: Are capital allocation decisions rational? | C14: Disciplined buybacks, reinvestment, and debt use. | D14: Buybacks at expensive prices while issuing stock comp. | E14: Buyback yield vs dilution | F14: Follow per-share results.
A15: Cyclicality | B15: Are you valuing peak or trough earnings? | C15: Normalized earnings across cycle. | D15: Peak EPS makes stock look cheap. | E15: Normalized EV/EBITDA | F15: Use multi-year averages.
A16: Sector fit | B16: Are you using the right model? | C16: Banks use residual/PB; software uses Rule of 40/DCF. | D16: Applying one formula to every business. | E16: Sector method map | F16: Choose metrics that match the business model.
A19: Common calculation mistakes
A20: Mistake | B20: Why it matters | C20: Fix
A21: Using Graham growth as decimal | B21: In the formula, 8% growth becomes 2g = 16, not 0.16. | C21: Use formula: 2 × growth rate × 100.
A22: Ignoring terminal assumptions | B22: Most DCF value often comes from the terminal value. | C22: Stress test discount rate and terminal growth.
A23: Using EBITDA when CapEx is heavy | B23: EBITDA can overstate cash generation. | C23: Check FCF and maintenance CapEx.
A24: Forgetting net debt | B24: Enterprise-value methods value the whole business. | C24: Subtract net debt before dividing by shares.
A25: Ignoring dilution | B25: Company growth may not equal shareholder growth. | C25: Track FCF per diluted share.
A26: Comparing P/E across unrelated sectors | B26: Different sectors deserve different multiples. | C26: Compare peers with similar margins, growth, and risks.

Sheet Sources & Notes
A1: Sources, Methodology Notes, and Data Hygiene
A3: No company-specific data has been sourced in this workbook. Example inputs are placeholders. Replace them with the latest company filings, investor presentations, and reliable market data before using the calculations.
A5: Reference links for formulas and concepts
A6: Topic | B6: Reference | C6: URL | D6: Notes
A7: Graham growth formula | B7: GrahamValue explanation | C7: https://www.grahamvalue.com/article/understanding-benjamin-graham-formula-correctly | D7: Use as a historical screening formula, not a standalone valuation.
A8: Free cash flow valuation | B8: CFA Institute refresher reading | C8: https://www.cfainstitute.org/insights/professional-learning/refresher-readings/free-cash-flow-valuation | D8: DCF and free cash flow model concepts.
A9: Residual income valuation | B9: CFA Institute refresher reading | C9: https://www.cfainstitute.org/insights/professional-learning/refresher-readings/residual-income-valuation | D9: Useful for book-value-heavy businesses.
A10: Equity valuation approaches | B10: CFA Institute refresher reading | C10: https://www.cfainstitute.org/insights/professional-learning/refresher-readings/equity-valuation-applications-and-processes | D10: Overview of absolute, relative, and sum-of-parts valuation.
A11: Financial ratios | B11: FINRA investor education | C11: https://www.finra.org/investors/insights/financial-performance-metrics-every-investor-should-know | D11: Basic ratio definitions and investor context.
A12: AAA corporate bond yield | B12: FRED DAAA series | C12: https://fred.stlouisfed.org/series/DAAA | D12: Use for the current AAA yield in the adjusted Graham formula.
A13: U.S. 10-year Treasury | B13: FRED GS10 series | C13: https://fred.stlouisfed.org/series/GS10 | D13: Useful benchmark for required returns and equity risk premium context.
A14: SaaS Rule of 40 | B14: McKinsey article | C14: https://www.mckinsey.com/industries/technology-media-and-telecommunications/our-insights/saas-and-the-rule-of-40-keys-to-the-critical-value-creation-metric | D14: Growth + margin framework for software/SaaS businesses.
A17: Data hygiene reminders
A18: Input type | B18: Where to source | C18: Common mistake | D18: Reminder
A19: EPS | B19: 10-K/10-Q, earnings release, reliable data provider | C19: Using one-time gains/losses as normal earnings | D19: Normalize unusual items.
A20: FCF | B20: Cash flow statement | C20: Ignoring stock-based compensation, working-capital swings, or maintenance CapEx | D20: Use consistent definition.
A21: Debt and cash | B21: Balance sheet and footnotes | C21: Forgetting leases, preferred stock, or minority interest | D21: Enterprise value methods require net debt.
A22: Shares | B22: Diluted shares from filings | C22: Using basic share count | D22: Per-share value uses diluted shares.
A23: Growth | B23: Historical results, guidance, industry outlook | C23: Projecting high growth forever | D23: Fade growth toward a realistic terminal rate.
A24: Discount rate | B24: Market rates and risk assessment | C24: Using a rate that is too low for the risk | D24: Stress test required return.
